{
  "project_info": {
    "project_number": "148953344813",
    "project_id": "simpleblog-6bc1a",
    "storage_bucket": "simpleblog-6bc1a.appspot.com"
  },
  "client": [
    {
      "client_info": {
        "mobilesdk_app_id": "1:148953344813:android:d31e849b651f594be0c1a4",
        "android_client_info": {
          "package_name": "com.example.simpleblog"
        }
      },
      "oauth_client": [
        {
          "client_id": "148953344813-a46q4noam08n6f0s2elsechkvut7m4ld.apps.googleusercontent.com",
          "client_type": 1,
          "android_info": {
            "package_name": "com.example.simpleblog",
            "certificate_hash": "eab7b129469b3db6f7258fd5fecd341d4aae194f"
          }
        },
        {
          "client_id": "148953344813-vn976pccn14pr84mntlb12m887ue2t1f.apps.googleusercontent.com",
          "client_type": 3
        }
      ],
      "api_key": [
        {
          "current_key": "AIzaSyAuSPLYtLg9hNPW22Y4eHIVRl46vNn5wT0"
        }
      ],
      "services": {
        "appinvite_service": {
          "other_platform_oauth_client": [
            {
              "client_id": "148953344813-vn976pccn14pr84mntlb12m887ue2t1f.apps.googleusercontent.com",
              "client_type": 3
            }
          ]
        }
      }
    }
  ],
  "configuration_version": "1"
}